pydio/__init__.py
pydio/_compat.py
pydio/_factories.py
pydio/_unbound_factories.py
pydio/api.py
pydio/base.py
pydio/exc.py
pydio/injector.py
pydio/keys.py
pydio/provider.py
pydio-0.4.1.dist-info/WHEEL
pydio-0.4.1.dist-info/METADATA
pydio-0.4.1.dist-info/LICENSE.txt
pydio-0.4.1.dist-info/RECORD
