Metadata-Version: 2.1
Name: pydio
Version: 0.4.1
Summary: Simple and functional dependency injection toolkit for Python
Home-page: https://github.com/mwiatrzyk/pydio
License: MIT
Keywords: dependency,injection,di,framework,toolkit,tool,library
Author: Maciej Wiatrzyk
Author-email: maciej.wiatrzyk@gmail.com
Requires-Python: >=3.7.2,<4
Classifier: Development Status :: 4 - Beta
Classifier: Intended Audience :: Developers
Classifier: License :: OSI Approved :: MIT License
Classifier: Operating System :: OS Independent
Classifier: Programming Language :: Python
Classifier: Programming Language :: Python :: 3
Classifier: Programming Language :: Python :: 3.8
Classifier: Programming Language :: Python :: 3.9
Classifier: Programming Language :: Python :: 3.10
Classifier: Programming Language :: Python :: 3.11
Classifier: Programming Language :: Python :: 3.10
Classifier: Programming Language :: Python :: 3.7
Classifier: Programming Language :: Python :: 3.8
Classifier: Programming Language :: Python :: 3.9
Project-URL: Documentation, https://pydio.readthedocs.io
Project-URL: Repository, https://github.com/mwiatrzyk/pydio
